Digital Design Using iVerilog/J-K Flip Flop/JK.v
module JK(J,K,clk,Q);
input wire J,K,clk;
output reg Q;

always@(posedge clk)
begin
if(J==1&&K==0)
Q=1;
else if(J==0&&K==1)
Q=0;
else if(J==1&&K==1)
Q=~Q;
else
Q=Q;
end

endmodule

Digital Design Using iVerilog/J-K Flip Flop/TJK.v
`timescale 1ns/100ps
module t_JK;
reg J,K,clk;
wire Q;
JK jk(.J(J), .K(K), .clk(clk), .Q(Q));

initial begin
$dumpfile("gtkJK.vcd");
$dumpvars(1,t_JK);

J=0;
K=0;
#8
J=0;K=1;
#10
J=0;K=0;
#10
J=1;K=0;
#10
J=1;K=1;
#10
J=1;K=1;

end

integer i;
initial begin
clk=0;
for(i=0;i<=10;i++)            //There are totally 11 half cycles of the clock, 6 negative and 5 positive. Each half cycle lasts for 10s
#10 clk=~clk;

end
endmodule

Digital Design Using iVerilog/J-K Flip Flop/gtkJK.vcd
$date
	Wed Nov 09 23:31:41 2016
$end
$version
	Icarus Verilog
$end
$timescale
	100ps
$end
$scope module t_JK $end
$var wire 1 ! Q $end
$var reg 1 " J $end
$var reg 1 # K $end
$var reg 1 $ clk $end
$var integer 32 % i [31:0] $end
$upscope $end
$enddefinitions $end
#0
$dumpvars
b0 %
0$
0#
0"
x!
$end
#80
1#
#100
0!
b1 %
1$
#180
0#
#200
b10 %
0$
#280
1"
#300
1!
b11 %
1$
#380
1#
#400
b100 %
0$
#500
0!
b101 %
1$
#600
b110 %
0$
#700
1!
b111 %
1$
#800
b1000 %
0$
#900
0!
b1001 %
1$
#1000
b1010 %
0$
#1100
1!
b1011 %
1$
